{"level":"info","message":"Server is listening on port 7000","timestamp":"2017-12-13T01:30:33.363Z"}
{"level":"info","message":"POST - processing REQUEST","timestamp":"2017-12-13T01:30:33.414Z"}
{"level":"info","message":"Server off","timestamp":"2017-12-13T01:30:33.441Z"}
{"level":"info","message":"Server is listening on port 7000","timestamp":"2017-12-13T01:30:56.599Z"}
{"level":"info","message":"POST - processing REQUEST","timestamp":"2017-12-13T01:30:56.650Z"}
{"level":"info","message":"POST - processing REQUEST","timestamp":"2017-12-13T01:30:56.680Z"}
{"level":"info","message":"POST - responding with 400 code","timestamp":"2017-12-13T01:30:56.680Z"}
{"level":"info","message":"GET - PROCESSING REQUEST","timestamp":"2017-12-13T01:30:56.689Z"}
{"level":"info","message":"GET -Return a 404, ID parsing failed","timestamp":"2017-12-13T01:30:56.692Z"}
{"level":"info","message":"GET - PROCESSING REQUEST","timestamp":"2017-12-13T01:30:56.694Z"}
{"level":"info","message":"GET - Returning a 404 status","timestamp":"2017-12-13T01:30:56.700Z"}
{"level":"info","message":"Server off","timestamp":"2017-12-13T01:30:56.701Z"}
{"level":"info","message":"Server is listening on port 7000","timestamp":"2017-12-13T01:31:03.964Z"}
{"level":"info","message":"POST - processing REQUEST","timestamp":"2017-12-13T01:31:04.011Z"}
{"level":"info","message":"POST - processing REQUEST","timestamp":"2017-12-13T01:31:04.041Z"}
{"level":"info","message":"POST - responding with 400 code","timestamp":"2017-12-13T01:31:04.041Z"}
{"level":"info","message":"GET - PROCESSING REQUEST","timestamp":"2017-12-13T01:31:04.049Z"}
{"level":"info","message":"GET -Return a 404, ID parsing failed","timestamp":"2017-12-13T01:31:04.052Z"}
{"level":"info","message":"GET - PROCESSING REQUEST","timestamp":"2017-12-13T01:31:04.054Z"}
{"level":"info","message":"GET - Returning a 404 status","timestamp":"2017-12-13T01:31:04.060Z"}
{"level":"info","message":"Server off","timestamp":"2017-12-13T01:31:04.061Z"}
{"level":"info","message":"Server is listening on port 7000","timestamp":"2017-12-13T01:31:08.133Z"}
{"level":"info","message":"POST - processing REQUEST","timestamp":"2017-12-13T01:31:08.180Z"}
{"level":"info","message":"POST - processing REQUEST","timestamp":"2017-12-13T01:31:08.208Z"}
{"level":"info","message":"POST - responding with 400 code","timestamp":"2017-12-13T01:31:08.208Z"}
{"level":"info","message":"GET - PROCESSING REQUEST","timestamp":"2017-12-13T01:31:08.215Z"}
{"level":"info","message":"GET -Return a 404, ID parsing failed","timestamp":"2017-12-13T01:31:08.218Z"}
{"level":"info","message":"GET - PROCESSING REQUEST","timestamp":"2017-12-13T01:31:08.221Z"}
{"level":"info","message":"GET - Returning a 404 status","timestamp":"2017-12-13T01:31:08.226Z"}
{"level":"info","message":"Server off","timestamp":"2017-12-13T01:31:08.228Z"}
{"level":"info","message":"Server is listening on port 7000","timestamp":"2017-12-13T01:31:12.803Z"}
{"level":"info","message":"POST - processing REQUEST","timestamp":"2017-12-13T01:31:12.848Z"}
{"level":"info","message":"POST - processing REQUEST","timestamp":"2017-12-13T01:31:12.878Z"}
{"level":"info","message":"POST - responding with 400 code","timestamp":"2017-12-13T01:31:12.878Z"}
{"level":"info","message":"GET - PROCESSING REQUEST","timestamp":"2017-12-13T01:31:12.886Z"}
{"level":"info","message":"GET -Return a 404, ID parsing failed","timestamp":"2017-12-13T01:31:12.889Z"}
{"level":"info","message":"GET - PROCESSING REQUEST","timestamp":"2017-12-13T01:31:12.891Z"}
{"level":"info","message":"GET - Returning a 404 status","timestamp":"2017-12-13T01:31:12.896Z"}
{"level":"info","message":"Server off","timestamp":"2017-12-13T01:31:12.898Z"}
{"level":"info","message":"Server is listening on port 7000","timestamp":"2017-12-13T01:31:17.257Z"}
{"level":"info","message":"POST - processing REQUEST","timestamp":"2017-12-13T01:31:17.305Z"}
{"level":"info","message":"POST - processing REQUEST","timestamp":"2017-12-13T01:31:17.335Z"}
{"level":"info","message":"POST - responding with 400 code","timestamp":"2017-12-13T01:31:17.335Z"}
{"level":"info","message":"GET - PROCESSING REQUEST","timestamp":"2017-12-13T01:31:17.342Z"}
{"level":"info","message":"GET -Return a 404, ID parsing failed","timestamp":"2017-12-13T01:31:17.346Z"}
{"level":"info","message":"GET - PROCESSING REQUEST","timestamp":"2017-12-13T01:31:17.348Z"}
{"level":"info","message":"GET - Returning a 404 status","timestamp":"2017-12-13T01:31:17.354Z"}
{"level":"info","message":"Server off","timestamp":"2017-12-13T01:31:17.355Z"}
{"level":"info","message":"Server is listening on port 7000","timestamp":"2017-12-13T01:31:22.043Z"}
{"level":"info","message":"POST - processing REQUEST","timestamp":"2017-12-13T01:31:22.088Z"}
{"level":"info","message":"POST - processing REQUEST","timestamp":"2017-12-13T01:31:22.117Z"}
{"level":"info","message":"POST - responding with 400 code","timestamp":"2017-12-13T01:31:22.117Z"}
{"level":"info","message":"GET - PROCESSING REQUEST","timestamp":"2017-12-13T01:31:22.125Z"}
{"level":"info","message":"GET -Return a 404, ID parsing failed","timestamp":"2017-12-13T01:31:22.129Z"}
{"level":"info","message":"GET - PROCESSING REQUEST","timestamp":"2017-12-13T01:31:22.131Z"}
{"level":"info","message":"GET - Returning a 404 status","timestamp":"2017-12-13T01:31:22.136Z"}
{"level":"info","message":"Server off","timestamp":"2017-12-13T01:31:22.137Z"}
{"level":"info","message":"Server is listening on port 7000","timestamp":"2017-12-13T01:31:27.022Z"}
{"level":"info","message":"POST - processing REQUEST","timestamp":"2017-12-13T01:31:27.067Z"}
{"level":"info","message":"POST - processing REQUEST","timestamp":"2017-12-13T01:31:27.096Z"}
{"level":"info","message":"POST - responding with 400 code","timestamp":"2017-12-13T01:31:27.096Z"}
{"level":"info","message":"GET - PROCESSING REQUEST","timestamp":"2017-12-13T01:31:27.104Z"}
{"level":"info","message":"GET -Return a 404, ID parsing failed","timestamp":"2017-12-13T01:31:27.107Z"}
{"level":"info","message":"GET - PROCESSING REQUEST","timestamp":"2017-12-13T01:31:27.109Z"}
{"level":"info","message":"GET - Returning a 404 status","timestamp":"2017-12-13T01:31:27.115Z"}
{"level":"info","message":"Server off","timestamp":"2017-12-13T01:31:27.116Z"}
{"level":"info","message":"Server is listening on port 7000","timestamp":"2017-12-13T01:31:31.169Z"}
{"level":"info","message":"POST - processing REQUEST","timestamp":"2017-12-13T01:31:31.216Z"}
{"level":"info","message":"POST - processing REQUEST","timestamp":"2017-12-13T01:31:31.244Z"}
{"level":"info","message":"POST - responding with 400 code","timestamp":"2017-12-13T01:31:31.244Z"}
{"level":"info","message":"GET - PROCESSING REQUEST","timestamp":"2017-12-13T01:31:31.253Z"}
{"level":"info","message":"GET -Return a 404, ID parsing failed","timestamp":"2017-12-13T01:31:31.256Z"}
{"level":"info","message":"GET - PROCESSING REQUEST","timestamp":"2017-12-13T01:31:31.259Z"}
{"level":"info","message":"GET - Returning a 404 status","timestamp":"2017-12-13T01:31:31.264Z"}
{"level":"info","message":"Server off","timestamp":"2017-12-13T01:31:31.266Z"}
{"level":"info","message":"Server is listening on port 7000","timestamp":"2017-12-13T01:34:17.000Z"}
{"level":"info","message":"POST - processing REQUEST","timestamp":"2017-12-13T01:34:17.045Z"}
{"level":"info","message":"POST - processing REQUEST","timestamp":"2017-12-13T01:34:17.074Z"}
{"level":"info","message":"POST - responding with 400 code","timestamp":"2017-12-13T01:34:17.074Z"}
{"level":"info","message":"GET - PROCESSING REQUEST","timestamp":"2017-12-13T01:34:17.083Z"}
{"level":"info","message":"GET - Return a 404, ID parsing failed","timestamp":"2017-12-13T01:34:17.086Z"}
{"level":"info","message":"GET - PROCESSING REQUEST","timestamp":"2017-12-13T01:34:17.088Z"}
{"level":"info","message":"GET - Returning a 404 status","timestamp":"2017-12-13T01:34:17.094Z"}
{"level":"info","message":"Server off","timestamp":"2017-12-13T01:34:17.096Z"}
{"level":"info","message":"Server is listening on port 7000","timestamp":"2017-12-13T01:35:21.785Z"}
{"level":"info","message":"POST - processing REQUEST","timestamp":"2017-12-13T01:35:21.835Z"}
{"level":"info","message":"POST - processing REQUEST","timestamp":"2017-12-13T01:35:21.864Z"}
{"level":"info","message":"POST - responding with 400 code","timestamp":"2017-12-13T01:35:21.864Z"}
{"level":"info","message":"GET - PROCESSING REQUEST","timestamp":"2017-12-13T01:35:21.870Z"}
{"level":"info","message":"GET - PROCESSING REQUEST","timestamp":"2017-12-13T01:35:21.881Z"}
{"level":"info","message":"GET - Return a 404, ID parsing failed","timestamp":"2017-12-13T01:35:21.883Z"}
{"level":"info","message":"GET - PROCESSING REQUEST","timestamp":"2017-12-13T01:35:21.888Z"}
{"level":"info","message":"Server off","timestamp":"2017-12-13T01:35:21.894Z"}
{"level":"info","message":"Server is listening on port 7000","timestamp":"2017-12-13T01:37:16.670Z"}
{"level":"info","message":"POST - processing REQUEST","timestamp":"2017-12-13T01:37:16.720Z"}
{"level":"info","message":"POST - processing REQUEST","timestamp":"2017-12-13T01:37:16.750Z"}
{"level":"info","message":"POST - responding with 400 code","timestamp":"2017-12-13T01:37:16.750Z"}
{"level":"info","message":"GET - PROCESSING REQUEST","timestamp":"2017-12-13T01:37:16.756Z"}
{"level":"info","message":"GET - PROCESSING REQUEST","timestamp":"2017-12-13T01:37:16.766Z"}
{"level":"info","message":"GET - Return a 404, ID parsing failed","timestamp":"2017-12-13T01:37:16.767Z"}
{"level":"info","message":"DELETE - PROCESSING REQUEST","timestamp":"2017-12-13T01:37:16.772Z"}
{"level":"error","message":"DELETE - Returning a 500 code","timestamp":"2017-12-13T01:37:16.775Z"}
{"message":"response.remove is not a function","stack":"TypeError: response.remove is not a function\n    at EpisodesModel.findById.then.episode (/home/cloud/Documents/codefellows/401/11-express-server/lab-jacob/route/star-trek-episodes-router.js:56:21)\n    at <anonymous>\n    at process._tickCallback (internal/process/next_tick.js:188:7)","level":"error","timestamp":"2017-12-13T01:37:16.775Z"}
{"level":"info","message":"Server off","timestamp":"2017-12-13T01:37:16.780Z"}
{"level":"info","message":"Server is listening on port 7000","timestamp":"2017-12-13T01:38:57.893Z"}
{"level":"info","message":"POST - processing REQUEST","timestamp":"2017-12-13T01:38:57.940Z"}
{"level":"info","message":"POST - processing REQUEST","timestamp":"2017-12-13T01:38:57.971Z"}
{"level":"info","message":"POST - responding with 400 code","timestamp":"2017-12-13T01:38:57.971Z"}
{"level":"info","message":"GET - PROCESSING REQUEST","timestamp":"2017-12-13T01:38:57.978Z"}
{"level":"info","message":"GET - PROCESSING REQUEST","timestamp":"2017-12-13T01:38:57.989Z"}
{"level":"info","message":"GET - Return a 404, ID parsing failed","timestamp":"2017-12-13T01:38:57.990Z"}
{"level":"info","message":"DELETE - PROCESSING REQUEST","timestamp":"2017-12-13T01:38:57.995Z"}
{"level":"info","message":"Server off","timestamp":"2017-12-13T01:38:58.001Z"}
{"level":"info","message":"Server is listening on port 7000","timestamp":"2017-12-13T01:49:47.553Z"}
{"level":"info","message":"POST - processing REQUEST","timestamp":"2017-12-13T01:49:47.604Z"}
{"level":"info","message":"POST - processing REQUEST","timestamp":"2017-12-13T01:49:47.638Z"}
{"level":"info","message":"POST - responding with 400 code","timestamp":"2017-12-13T01:49:47.638Z"}
{"level":"info","message":"GET - PROCESSING REQUEST","timestamp":"2017-12-13T01:49:47.644Z"}
{"level":"info","message":"GET - PROCESSING REQUEST","timestamp":"2017-12-13T01:49:47.654Z"}
{"level":"info","message":"GET - Return a 404, ID parsing failed","timestamp":"2017-12-13T01:49:47.656Z"}
{"level":"info","message":"DELETE - PROCESSING REQUEST","timestamp":"2017-12-13T01:49:47.661Z"}
{"level":"info","message":"Server off","timestamp":"2017-12-13T01:49:47.667Z"}
{"level":"info","message":"Server is listening on port 7000","timestamp":"2017-12-13T01:58:15.695Z"}
{"level":"info","message":"POST - processing REQUEST","timestamp":"2017-12-13T01:58:15.737Z"}
{"level":"info","message":"POST - processing REQUEST","timestamp":"2017-12-13T01:58:15.766Z"}
{"level":"info","message":"POST - responding with 400 code","timestamp":"2017-12-13T01:58:15.766Z"}
{"level":"info","message":"GET - PROCESSING REQUEST","timestamp":"2017-12-13T01:58:15.773Z"}
{"level":"info","message":"GET - PROCESSING REQUEST","timestamp":"2017-12-13T01:58:15.784Z"}
{"level":"info","message":"GET - Return a 404, ID parsing failed","timestamp":"2017-12-13T01:58:15.785Z"}
{"level":"info","message":"DELETE - PROCESSING REQUEST","timestamp":"2017-12-13T01:58:15.789Z"}
{"level":"info","message":"Server off","timestamp":"2017-12-13T01:58:15.794Z"}
{"level":"info","message":"Server is listening on port 7000","timestamp":"2017-12-13T01:58:38.226Z"}
{"level":"info","message":"POST - processing REQUEST","timestamp":"2017-12-13T01:58:38.269Z"}
{"level":"info","message":"POST - processing REQUEST","timestamp":"2017-12-13T01:58:38.299Z"}
{"level":"info","message":"POST - responding with 400 code","timestamp":"2017-12-13T01:58:38.299Z"}
{"level":"info","message":"GET - PROCESSING REQUEST","timestamp":"2017-12-13T01:58:38.305Z"}
{"level":"info","message":"GET - PROCESSING REQUEST","timestamp":"2017-12-13T01:58:38.315Z"}
{"level":"info","message":"GET - Return a 404, ID parsing failed","timestamp":"2017-12-13T01:58:38.316Z"}
{"level":"info","message":"DELETE - PROCESSING REQUEST","timestamp":"2017-12-13T01:58:38.320Z"}
{"level":"info","message":"Server off","timestamp":"2017-12-13T01:58:38.326Z"}
{"level":"info","message":"Server is listening on port 7000","timestamp":"2017-12-13T02:01:15.253Z"}
{"level":"info","message":"POST - processing REQUEST","timestamp":"2017-12-13T02:01:15.298Z"}
{"level":"info","message":"POST - processing REQUEST","timestamp":"2017-12-13T02:01:15.327Z"}
{"level":"info","message":"POST - responding with 400 code","timestamp":"2017-12-13T02:01:15.327Z"}
{"level":"info","message":"GET - PROCESSING REQUEST","timestamp":"2017-12-13T02:01:15.333Z"}
{"level":"info","message":"GET - PROCESSING REQUEST","timestamp":"2017-12-13T02:01:15.344Z"}
{"level":"info","message":"GET - Return a 404, ID parsing failed","timestamp":"2017-12-13T02:01:15.345Z"}
{"level":"info","message":"DELETE - PROCESSING REQUEST","timestamp":"2017-12-13T02:01:15.350Z"}
{"level":"info","message":"Server off","timestamp":"2017-12-13T02:01:15.356Z"}
{"level":"info","message":"Server is listening on port 7000","timestamp":"2017-12-13T02:12:27.558Z"}
{"level":"info","message":"POST - processing REQUEST","timestamp":"2017-12-13T02:12:27.603Z"}
{"level":"info","message":"POST - processing REQUEST","timestamp":"2017-12-13T02:12:27.632Z"}
{"level":"info","message":"POST - responding with 400 code","timestamp":"2017-12-13T02:12:27.632Z"}
{"level":"info","message":"GET - PROCESSING REQUEST","timestamp":"2017-12-13T02:12:27.639Z"}
{"level":"info","message":"GET - PROCESSING REQUEST","timestamp":"2017-12-13T02:12:27.649Z"}
{"level":"info","message":"GET - Return a 404, ID parsing failed","timestamp":"2017-12-13T02:12:27.650Z"}
{"level":"info","message":"GET - PROCESSING REQUEST","timestamp":"2017-12-13T02:12:27.654Z"}
{"level":"info","message":"DELETE - PROCESSING REQUEST","timestamp":"2017-12-13T02:12:27.660Z"}
{"level":"info","message":"Server off","timestamp":"2017-12-13T02:12:27.666Z"}
{"level":"info","message":"Server is listening on port 7000","timestamp":"2017-12-13T02:49:31.989Z"}
{"level":"info","message":"POST - processing REQUEST","timestamp":"2017-12-13T02:49:32.040Z"}
{"level":"info","message":"POST - processing REQUEST","timestamp":"2017-12-13T02:49:32.069Z"}
{"level":"info","message":"POST - responding with 400 code","timestamp":"2017-12-13T02:49:32.069Z"}
{"level":"info","message":"404 from Catch-All route","timestamp":"2017-12-13T02:49:32.075Z"}
{"level":"info","message":"GET - PROCESSING REQUEST","timestamp":"2017-12-13T02:49:32.080Z"}
{"level":"info","message":"GET - PROCESSING REQUEST","timestamp":"2017-12-13T02:49:32.094Z"}
{"level":"info","message":"GET - Return a 404, ID parsing failed","timestamp":"2017-12-13T02:49:32.095Z"}
{"level":"info","message":"GET - PROCESSING REQUEST","timestamp":"2017-12-13T02:49:32.102Z"}
{"level":"info","message":"DELETE - PROCESSING REQUEST","timestamp":"2017-12-13T02:49:32.111Z"}
{"level":"info","message":"Server off","timestamp":"2017-12-13T02:49:32.119Z"}
{"level":"info","message":"Server is listening on port 7000","timestamp":"2017-12-13T02:56:03.369Z"}
{"level":"info","message":"POST - processing REQUEST","timestamp":"2017-12-13T02:56:03.420Z"}
{"level":"info","message":"POST - processing REQUEST","timestamp":"2017-12-13T02:56:03.449Z"}
{"level":"info","message":"POST - responding with 400 code","timestamp":"2017-12-13T02:56:03.449Z"}
{"level":"info","message":"404 from Catch-All route","timestamp":"2017-12-13T02:56:03.456Z"}
{"level":"info","message":"GET - PROCESSING REQUEST","timestamp":"2017-12-13T02:56:03.462Z"}
{"level":"info","message":"GET - PROCESSING REQUEST","timestamp":"2017-12-13T02:56:03.474Z"}
{"level":"info","message":"GET - Return a 404, ID parsing failed","timestamp":"2017-12-13T02:56:03.475Z"}
{"level":"info","message":"GET - PROCESSING REQUEST","timestamp":"2017-12-13T02:56:03.480Z"}
{"level":"info","message":"DELETE - PROCESSING REQUEST","timestamp":"2017-12-13T02:56:03.500Z"}
{"level":"info","message":"Server off","timestamp":"2017-12-13T02:56:03.507Z"}
{"level":"info","message":"Server is listening on port 7000","timestamp":"2017-12-13T02:56:50.936Z"}
{"level":"info","message":"POST - processing REQUEST","timestamp":"2017-12-13T02:56:50.987Z"}
{"level":"info","message":"POST - processing REQUEST","timestamp":"2017-12-13T02:56:51.015Z"}
{"level":"info","message":"POST - responding with 400 code","timestamp":"2017-12-13T02:56:51.015Z"}
{"level":"info","message":"404 from Catch-All route","timestamp":"2017-12-13T02:56:51.021Z"}
{"level":"info","message":"GET - PROCESSING REQUEST","timestamp":"2017-12-13T02:56:51.026Z"}
{"level":"info","message":"GET - PROCESSING REQUEST","timestamp":"2017-12-13T02:56:51.037Z"}
{"level":"info","message":"GET - Return a 404, ID parsing failed","timestamp":"2017-12-13T02:56:51.039Z"}
{"level":"info","message":"GET - PROCESSING REQUEST","timestamp":"2017-12-13T02:56:51.047Z"}
{"level":"info","message":"DELETE - PROCESSING REQUEST","timestamp":"2017-12-13T02:56:51.064Z"}
{"level":"info","message":"Server off","timestamp":"2017-12-13T02:56:51.072Z"}
{"level":"info","message":"Server is listening on port 7000","timestamp":"2017-12-13T02:58:04.349Z"}
{"level":"info","message":"POST - processing REQUEST","timestamp":"2017-12-13T02:58:04.394Z"}
{"level":"info","message":"POST - processing REQUEST","timestamp":"2017-12-13T02:58:04.421Z"}
{"level":"info","message":"POST - responding with 400 code","timestamp":"2017-12-13T02:58:04.422Z"}
{"level":"info","message":"404 from Catch-All route","timestamp":"2017-12-13T02:58:04.428Z"}
{"level":"info","message":"GET - PROCESSING REQUEST","timestamp":"2017-12-13T02:58:04.433Z"}
{"level":"info","message":"GET - PROCESSING REQUEST","timestamp":"2017-12-13T02:58:04.445Z"}
{"level":"info","message":"GET - Return a 404, ID parsing failed","timestamp":"2017-12-13T02:58:04.446Z"}
{"level":"info","message":"GET - PROCESSING REQUEST","timestamp":"2017-12-13T02:58:04.451Z"}
{"level":"info","message":"DELETE - PROCESSING REQUEST","timestamp":"2017-12-13T02:58:04.463Z"}
{"level":"info","message":"Server off","timestamp":"2017-12-13T02:58:04.470Z"}
{"level":"info","message":"Server is listening on port 7000","timestamp":"2017-12-13T03:00:35.102Z"}
{"level":"info","message":"POST - processing REQUEST","timestamp":"2017-12-13T03:00:35.149Z"}
{"level":"info","message":"POST - processing REQUEST","timestamp":"2017-12-13T03:00:35.182Z"}
{"level":"info","message":"POST - responding with 400 code","timestamp":"2017-12-13T03:00:35.182Z"}
{"level":"info","message":"404 from Catch-All route","timestamp":"2017-12-13T03:00:35.188Z"}
{"level":"info","message":"GET - PROCESSING REQUEST","timestamp":"2017-12-13T03:00:35.193Z"}
{"level":"info","message":"GET - PROCESSING REQUEST","timestamp":"2017-12-13T03:00:35.203Z"}
{"level":"info","message":"GET - Return a 404, ID parsing failed","timestamp":"2017-12-13T03:00:35.205Z"}
{"level":"info","message":"GET - PROCESSING REQUEST","timestamp":"2017-12-13T03:00:35.209Z"}
{"level":"info","message":"DELETE - PROCESSING REQUEST","timestamp":"2017-12-13T03:00:35.221Z"}
{"level":"info","message":"Server off","timestamp":"2017-12-13T03:00:35.230Z"}
{"level":"info","message":"Server is listening on port 7000","timestamp":"2017-12-13T03:04:18.240Z"}
{"level":"info","message":"POST - processing REQUEST","timestamp":"2017-12-13T03:04:18.288Z"}
{"level":"info","message":"POST - processing REQUEST","timestamp":"2017-12-13T03:04:18.322Z"}
{"level":"info","message":"POST - responding with 400 code","timestamp":"2017-12-13T03:04:18.322Z"}
{"level":"info","message":"404 from Catch-All route","timestamp":"2017-12-13T03:04:18.329Z"}
{"level":"info","message":"GET - PROCESSING REQUEST","timestamp":"2017-12-13T03:04:18.334Z"}
{"level":"info","message":"GET - PROCESSING REQUEST","timestamp":"2017-12-13T03:04:18.345Z"}
{"level":"info","message":"GET - Return a 404, ID parsing failed","timestamp":"2017-12-13T03:04:18.347Z"}
{"level":"info","message":"DELETE - PROCESSING REQUEST","timestamp":"2017-12-13T03:04:18.359Z"}
{"level":"info","message":"Server off","timestamp":"2017-12-13T03:04:18.366Z"}
{"level":"info","message":"Server is listening on port 7000","timestamp":"2017-12-13T04:30:07.281Z"}
{"level":"info","message":"__ERROR_MIDDLEWARE__","timestamp":"2017-12-13T04:30:07.353Z"}
{"message":"body and content are required","stack":"BadRequestError: body and content are required\n    at Object.<anonymous>.starTrekEpisodesRouter.post (/home/cloud/Documents/codefellows/401/11-express-server/lab-jacob/route/star-trek-episodes-router.js:52:17)\n    at Layer.handle [as handle_request] (/home/cloud/Documents/codefellows/401/11-express-server/lab-jacob/node_modules/express/lib/router/layer.js:95:5)\n    at next (/home/cloud/Documents/codefellows/401/11-express-server/lab-jacob/node_modules/express/lib/router/route.js:137:13)\n    at /home/cloud/Documents/codefellows/401/11-express-server/lab-jacob/node_modules/body-parser/lib/read.js:130:5\n    at invokeCallback (/home/cloud/Documents/codefellows/401/11-express-server/lab-jacob/node_modules/raw-body/index.js:224:16)\n    at done (/home/cloud/Documents/codefellows/401/11-express-server/lab-jacob/node_modules/raw-body/index.js:213:7)\n    at IncomingMessage.onEnd (/home/cloud/Documents/codefellows/401/11-express-server/lab-jacob/node_modules/raw-body/index.js:273:7)\n    at emitNone (events.js:106:13)\n    at IncomingMessage.emit (events.js:208:7)\n    at endReadableNT (_stream_readable.js:1056:12)\n    at _combinedTickCallback (internal/process/next_tick.js:138:11)\n    at process._tickCallback (internal/process/next_tick.js:180:9)","name":"BadRequestError","level":"info","timestamp":"2017-12-13T04:30:07.353Z"}
{"level":"info","message":"Responding with a 400 status and message: body and content are required","timestamp":"2017-12-13T04:30:07.354Z"}
{"level":"info","message":"GET - PROCESSING REQUEST","timestamp":"2017-12-13T04:30:07.373Z"}
{"level":"info","message":"GET - PROCESSING REQUEST","timestamp":"2017-12-13T04:30:07.382Z"}
{"level":"info","message":"GET - Return a 404, ID parsing failed","timestamp":"2017-12-13T04:30:07.383Z"}
{"level":"info","message":"GET - PROCESSING REQUEST","timestamp":"2017-12-13T04:30:07.388Z"}
{"level":"info","message":"Server off","timestamp":"2017-12-13T04:30:07.408Z"}
{"level":"info","message":"Server is listening on port 7000","timestamp":"2017-12-13T04:47:57.863Z"}
{"level":"info","message":"__ERROR_MIDDLEWARE__","timestamp":"2017-12-13T04:47:57.934Z"}
{"message":"body and content are required","stack":"BadRequestError: body and content are required\n    at Object.<anonymous>.starTrekEpisodesRouter.post (/home/cloud/Documents/codefellows/401/11-express-server/lab-jacob/route/star-trek-episodes-router.js:52:17)\n    at Layer.handle [as handle_request] (/home/cloud/Documents/codefellows/401/11-express-server/lab-jacob/node_modules/express/lib/router/layer.js:95:5)\n    at next (/home/cloud/Documents/codefellows/401/11-express-server/lab-jacob/node_modules/express/lib/router/route.js:137:13)\n    at /home/cloud/Documents/codefellows/401/11-express-server/lab-jacob/node_modules/body-parser/lib/read.js:130:5\n    at invokeCallback (/home/cloud/Documents/codefellows/401/11-express-server/lab-jacob/node_modules/raw-body/index.js:224:16)\n    at done (/home/cloud/Documents/codefellows/401/11-express-server/lab-jacob/node_modules/raw-body/index.js:213:7)\n    at IncomingMessage.onEnd (/home/cloud/Documents/codefellows/401/11-express-server/lab-jacob/node_modules/raw-body/index.js:273:7)\n    at emitNone (events.js:106:13)\n    at IncomingMessage.emit (events.js:208:7)\n    at endReadableNT (_stream_readable.js:1056:12)\n    at _combinedTickCallback (internal/process/next_tick.js:138:11)\n    at process._tickCallback (internal/process/next_tick.js:180:9)","name":"BadRequestError","level":"info","timestamp":"2017-12-13T04:47:57.934Z"}
{"level":"info","message":"Responding with a 400 status and message: body and content are required","timestamp":"2017-12-13T04:47:57.934Z"}
{"level":"info","message":"__ERROR_MIDDLEWARE__","timestamp":"2017-12-13T04:47:57.962Z"}
{"message":"Cast to ObjectId failed for value \"WRONG_ID\" at path \"_id\" for model \"episode\"","stack":"CastError: Cast to ObjectId failed for value \"WRONG_ID\" at path \"_id\" for model \"episode\"\n    at new CastError (/home/cloud/Documents/codefellows/401/11-express-server/lab-jacob/node_modules/mongoose/lib/error/cast.js:27:11)\n    at ObjectId.Object.<anonymous>.ObjectId.cast (/home/cloud/Documents/codefellows/401/11-express-server/lab-jacob/node_modules/mongoose/lib/schema/objectid.js:158:13)\n    at ObjectId.Object.<anonymous>.SchemaType._castForQuery (/home/cloud/Documents/codefellows/401/11-express-server/lab-jacob/node_modules/mongoose/lib/schematype.js:1088:15)\n    at ObjectId.Object.<anonymous>.ObjectId.castForQuery (/home/cloud/Documents/codefellows/401/11-express-server/lab-jacob/node_modules/mongoose/lib/schema/objectid.js:198:15)\n    at ObjectId.Object.<anonymous>.SchemaType.castForQueryWrapper (/home/cloud/Documents/codefellows/401/11-express-server/lab-jacob/node_modules/mongoose/lib/schematype.js:1045:15)\n    at cast (/home/cloud/Documents/codefellows/401/11-express-server/lab-jacob/node_modules/mongoose/lib/cast.js:269:32)\n    at model.Query.Object.<anonymous>.Query.cast (/home/cloud/Documents/codefellows/401/11-express-server/lab-jacob/node_modules/mongoose/lib/query.js:3302:12)\n    at model.Query.Object.<anonymous>.Query._castConditions (/home/cloud/Documents/codefellows/401/11-express-server/lab-jacob/node_modules/mongoose/lib/query.js:1292:10)\n    at model.Query.Object.<anonymous>.Query._findOne (/home/cloud/Documents/codefellows/401/11-express-server/lab-jacob/node_modules/mongoose/lib/query.js:1504:8)\n    at /home/cloud/Documents/codefellows/401/11-express-server/lab-jacob/node_modules/kareem/index.js:250:8\n    at /home/cloud/Documents/codefellows/401/11-express-server/lab-jacob/node_modules/kareem/index.js:23:7\n    at _combinedTickCallback (internal/process/next_tick.js:131:7)\n    at process._tickCallback (internal/process/next_tick.js:180:9)","name":"CastError","stringValue":"\"WRONG_ID\"","kind":"ObjectId","value":"WRONG_ID","path":"_id","level":"info","timestamp":"2017-12-13T04:47:57.962Z"}
{"level":"info","message":"Responding with a 404 status code","timestamp":"2017-12-13T04:47:57.963Z"}
{"level":"info","message":"Server off","timestamp":"2017-12-13T04:47:57.985Z"}
{"level":"info","message":"Server is listening on port 7000","timestamp":"2017-12-13T04:49:19.971Z"}
{"level":"info","message":"__ERROR_MIDDLEWARE__","timestamp":"2017-12-13T04:49:20.046Z"}
{"message":"body and content are required","stack":"BadRequestError: body and content are required\n    at Object.<anonymous>.starTrekEpisodesRouter.post (/home/cloud/Documents/codefellows/401/11-express-server/lab-jacob/route/star-trek-episodes-router.js:52:17)\n    at Layer.handle [as handle_request] (/home/cloud/Documents/codefellows/401/11-express-server/lab-jacob/node_modules/express/lib/router/layer.js:95:5)\n    at next (/home/cloud/Documents/codefellows/401/11-express-server/lab-jacob/node_modules/express/lib/router/route.js:137:13)\n    at /home/cloud/Documents/codefellows/401/11-express-server/lab-jacob/node_modules/body-parser/lib/read.js:130:5\n    at invokeCallback (/home/cloud/Documents/codefellows/401/11-express-server/lab-jacob/node_modules/raw-body/index.js:224:16)\n    at done (/home/cloud/Documents/codefellows/401/11-express-server/lab-jacob/node_modules/raw-body/index.js:213:7)\n    at IncomingMessage.onEnd (/home/cloud/Documents/codefellows/401/11-express-server/lab-jacob/node_modules/raw-body/index.js:273:7)\n    at emitNone (events.js:106:13)\n    at IncomingMessage.emit (events.js:208:7)\n    at endReadableNT (_stream_readable.js:1056:12)\n    at _combinedTickCallback (internal/process/next_tick.js:138:11)\n    at process._tickCallback (internal/process/next_tick.js:180:9)","name":"BadRequestError","level":"info","timestamp":"2017-12-13T04:49:20.046Z"}
{"level":"info","message":"Responding with a 400 status and message: body and content are required","timestamp":"2017-12-13T04:49:20.047Z"}
{"level":"info","message":"__ERROR_MIDDLEWARE__","timestamp":"2017-12-13T04:49:20.073Z"}
{"message":"Cast to ObjectId failed for value \"WRONG_ID\" at path \"_id\" for model \"episode\"","stack":"CastError: Cast to ObjectId failed for value \"WRONG_ID\" at path \"_id\" for model \"episode\"\n    at new CastError (/home/cloud/Documents/codefellows/401/11-express-server/lab-jacob/node_modules/mongoose/lib/error/cast.js:27:11)\n    at ObjectId.Object.<anonymous>.ObjectId.cast (/home/cloud/Documents/codefellows/401/11-express-server/lab-jacob/node_modules/mongoose/lib/schema/objectid.js:158:13)\n    at ObjectId.Object.<anonymous>.SchemaType._castForQuery (/home/cloud/Documents/codefellows/401/11-express-server/lab-jacob/node_modules/mongoose/lib/schematype.js:1088:15)\n    at ObjectId.Object.<anonymous>.ObjectId.castForQuery (/home/cloud/Documents/codefellows/401/11-express-server/lab-jacob/node_modules/mongoose/lib/schema/objectid.js:198:15)\n    at ObjectId.Object.<anonymous>.SchemaType.castForQueryWrapper (/home/cloud/Documents/codefellows/401/11-express-server/lab-jacob/node_modules/mongoose/lib/schematype.js:1045:15)\n    at cast (/home/cloud/Documents/codefellows/401/11-express-server/lab-jacob/node_modules/mongoose/lib/cast.js:269:32)\n    at model.Query.Object.<anonymous>.Query.cast (/home/cloud/Documents/codefellows/401/11-express-server/lab-jacob/node_modules/mongoose/lib/query.js:3302:12)\n    at model.Query.Object.<anonymous>.Query._castConditions (/home/cloud/Documents/codefellows/401/11-express-server/lab-jacob/node_modules/mongoose/lib/query.js:1292:10)\n    at model.Query.Object.<anonymous>.Query._findOne (/home/cloud/Documents/codefellows/401/11-express-server/lab-jacob/node_modules/mongoose/lib/query.js:1504:8)\n    at /home/cloud/Documents/codefellows/401/11-express-server/lab-jacob/node_modules/kareem/index.js:250:8\n    at /home/cloud/Documents/codefellows/401/11-express-server/lab-jacob/node_modules/kareem/index.js:23:7\n    at _combinedTickCallback (internal/process/next_tick.js:131:7)\n    at process._tickCallback (internal/process/next_tick.js:180:9)","name":"CastError","stringValue":"\"WRONG_ID\"","kind":"ObjectId","value":"WRONG_ID","path":"_id","level":"info","timestamp":"2017-12-13T04:49:20.073Z"}
{"level":"info","message":"Responding with a 404 status code","timestamp":"2017-12-13T04:49:20.074Z"}
{"level":"info","message":"Server off","timestamp":"2017-12-13T04:49:20.094Z"}
{"level":"info","message":"Server is listening on port 7000","timestamp":"2017-12-13T04:50:52.619Z"}
{"level":"info","message":"__ERROR_MIDDLEWARE__","timestamp":"2017-12-13T04:50:52.693Z"}
{"message":"body and content are required","stack":"BadRequestError: body and content are required\n    at Object.<anonymous>.starTrekEpisodesRouter.post (/home/cloud/Documents/codefellows/401/11-express-server/lab-jacob/route/star-trek-episodes-router.js:52:17)\n    at Layer.handle [as handle_request] (/home/cloud/Documents/codefellows/401/11-express-server/lab-jacob/node_modules/express/lib/router/layer.js:95:5)\n    at next (/home/cloud/Documents/codefellows/401/11-express-server/lab-jacob/node_modules/express/lib/router/route.js:137:13)\n    at /home/cloud/Documents/codefellows/401/11-express-server/lab-jacob/node_modules/body-parser/lib/read.js:130:5\n    at invokeCallback (/home/cloud/Documents/codefellows/401/11-express-server/lab-jacob/node_modules/raw-body/index.js:224:16)\n    at done (/home/cloud/Documents/codefellows/401/11-express-server/lab-jacob/node_modules/raw-body/index.js:213:7)\n    at IncomingMessage.onEnd (/home/cloud/Documents/codefellows/401/11-express-server/lab-jacob/node_modules/raw-body/index.js:273:7)\n    at emitNone (events.js:106:13)\n    at IncomingMessage.emit (events.js:208:7)\n    at endReadableNT (_stream_readable.js:1056:12)\n    at _combinedTickCallback (internal/process/next_tick.js:138:11)\n    at process._tickCallback (internal/process/next_tick.js:180:9)","name":"BadRequestError","level":"info","timestamp":"2017-12-13T04:50:52.693Z"}
{"level":"info","message":"Responding with a 400 status and message: body and content are required","timestamp":"2017-12-13T04:50:52.694Z"}
{"level":"info","message":"__ERROR_MIDDLEWARE__","timestamp":"2017-12-13T04:50:52.720Z"}
{"message":"Cast to ObjectId failed for value \"WRONG_ID\" at path \"_id\" for model \"episode\"","stack":"CastError: Cast to ObjectId failed for value \"WRONG_ID\" at path \"_id\" for model \"episode\"\n    at new CastError (/home/cloud/Documents/codefellows/401/11-express-server/lab-jacob/node_modules/mongoose/lib/error/cast.js:27:11)\n    at ObjectId.Object.<anonymous>.ObjectId.cast (/home/cloud/Documents/codefellows/401/11-express-server/lab-jacob/node_modules/mongoose/lib/schema/objectid.js:158:13)\n    at ObjectId.Object.<anonymous>.SchemaType._castForQuery (/home/cloud/Documents/codefellows/401/11-express-server/lab-jacob/node_modules/mongoose/lib/schematype.js:1088:15)\n    at ObjectId.Object.<anonymous>.ObjectId.castForQuery (/home/cloud/Documents/codefellows/401/11-express-server/lab-jacob/node_modules/mongoose/lib/schema/objectid.js:198:15)\n    at ObjectId.Object.<anonymous>.SchemaType.castForQueryWrapper (/home/cloud/Documents/codefellows/401/11-express-server/lab-jacob/node_modules/mongoose/lib/schematype.js:1045:15)\n    at cast (/home/cloud/Documents/codefellows/401/11-express-server/lab-jacob/node_modules/mongoose/lib/cast.js:269:32)\n    at model.Query.Object.<anonymous>.Query.cast (/home/cloud/Documents/codefellows/401/11-express-server/lab-jacob/node_modules/mongoose/lib/query.js:3302:12)\n    at model.Query.Object.<anonymous>.Query._castConditions (/home/cloud/Documents/codefellows/401/11-express-server/lab-jacob/node_modules/mongoose/lib/query.js:1292:10)\n    at model.Query.Object.<anonymous>.Query._findOne (/home/cloud/Documents/codefellows/401/11-express-server/lab-jacob/node_modules/mongoose/lib/query.js:1504:8)\n    at /home/cloud/Documents/codefellows/401/11-express-server/lab-jacob/node_modules/kareem/index.js:250:8\n    at /home/cloud/Documents/codefellows/401/11-express-server/lab-jacob/node_modules/kareem/index.js:23:7\n    at _combinedTickCallback (internal/process/next_tick.js:131:7)\n    at process._tickCallback (internal/process/next_tick.js:180:9)","name":"CastError","stringValue":"\"WRONG_ID\"","kind":"ObjectId","value":"WRONG_ID","path":"_id","level":"info","timestamp":"2017-12-13T04:50:52.720Z"}
{"level":"info","message":"Responding with a 404 status code","timestamp":"2017-12-13T04:50:52.721Z"}
{"level":"info","message":"Server off","timestamp":"2017-12-13T04:50:52.742Z"}
{"level":"info","message":"Server is listening on port 7000","timestamp":"2017-12-13T04:51:58.416Z"}
{"level":"info","message":"__ERROR_MIDDLEWARE__","timestamp":"2017-12-13T04:51:58.515Z"}
{"message":"body and content are required","stack":"BadRequestError: body and content are required\n    at Object.<anonymous>.starTrekEpisodesRouter.post (/home/cloud/Documents/codefellows/401/11-express-server/lab-jacob/route/star-trek-episodes-router.js:52:17)\n    at Layer.handle [as handle_request] (/home/cloud/Documents/codefellows/401/11-express-server/lab-jacob/node_modules/express/lib/router/layer.js:95:5)\n    at next (/home/cloud/Documents/codefellows/401/11-express-server/lab-jacob/node_modules/express/lib/router/route.js:137:13)\n    at /home/cloud/Documents/codefellows/401/11-express-server/lab-jacob/node_modules/body-parser/lib/read.js:130:5\n    at invokeCallback (/home/cloud/Documents/codefellows/401/11-express-server/lab-jacob/node_modules/raw-body/index.js:224:16)\n    at done (/home/cloud/Documents/codefellows/401/11-express-server/lab-jacob/node_modules/raw-body/index.js:213:7)\n    at IncomingMessage.onEnd (/home/cloud/Documents/codefellows/401/11-express-server/lab-jacob/node_modules/raw-body/index.js:273:7)\n    at emitNone (events.js:106:13)\n    at IncomingMessage.emit (events.js:208:7)\n    at endReadableNT (_stream_readable.js:1056:12)\n    at _combinedTickCallback (internal/process/next_tick.js:138:11)\n    at process._tickCallback (internal/process/next_tick.js:180:9)","name":"BadRequestError","level":"info","timestamp":"2017-12-13T04:51:58.515Z"}
{"level":"info","message":"Responding with a 400 status and message: body and content are required","timestamp":"2017-12-13T04:51:58.516Z"}
{"level":"info","message":"__ERROR_MIDDLEWARE__","timestamp":"2017-12-13T04:51:58.550Z"}
{"message":"Cast to ObjectId failed for value \"WRONG_ID\" at path \"_id\" for model \"episode\"","stack":"CastError: Cast to ObjectId failed for value \"WRONG_ID\" at path \"_id\" for model \"episode\"\n    at new CastError (/home/cloud/Documents/codefellows/401/11-express-server/lab-jacob/node_modules/mongoose/lib/error/cast.js:27:11)\n    at ObjectId.Object.<anonymous>.ObjectId.cast (/home/cloud/Documents/codefellows/401/11-express-server/lab-jacob/node_modules/mongoose/lib/schema/objectid.js:158:13)\n    at ObjectId.Object.<anonymous>.SchemaType._castForQuery (/home/cloud/Documents/codefellows/401/11-express-server/lab-jacob/node_modules/mongoose/lib/schematype.js:1088:15)\n    at ObjectId.Object.<anonymous>.ObjectId.castForQuery (/home/cloud/Documents/codefellows/401/11-express-server/lab-jacob/node_modules/mongoose/lib/schema/objectid.js:198:15)\n    at ObjectId.Object.<anonymous>.SchemaType.castForQueryWrapper (/home/cloud/Documents/codefellows/401/11-express-server/lab-jacob/node_modules/mongoose/lib/schematype.js:1045:15)\n    at cast (/home/cloud/Documents/codefellows/401/11-express-server/lab-jacob/node_modules/mongoose/lib/cast.js:269:32)\n    at model.Query.Object.<anonymous>.Query.cast (/home/cloud/Documents/codefellows/401/11-express-server/lab-jacob/node_modules/mongoose/lib/query.js:3302:12)\n    at model.Query.Object.<anonymous>.Query._castConditions (/home/cloud/Documents/codefellows/401/11-express-server/lab-jacob/node_modules/mongoose/lib/query.js:1292:10)\n    at model.Query.Object.<anonymous>.Query._findOne (/home/cloud/Documents/codefellows/401/11-express-server/lab-jacob/node_modules/mongoose/lib/query.js:1504:8)\n    at /home/cloud/Documents/codefellows/401/11-express-server/lab-jacob/node_modules/kareem/index.js:250:8\n    at /home/cloud/Documents/codefellows/401/11-express-server/lab-jacob/node_modules/kareem/index.js:23:7\n    at _combinedTickCallback (internal/process/next_tick.js:131:7)\n    at process._tickCallback (internal/process/next_tick.js:180:9)","name":"CastError","stringValue":"\"WRONG_ID\"","kind":"ObjectId","value":"WRONG_ID","path":"_id","level":"info","timestamp":"2017-12-13T04:51:58.550Z"}
{"level":"info","message":"Responding with a 404 status code","timestamp":"2017-12-13T04:51:58.550Z"}
{"level":"info","message":"Server off","timestamp":"2017-12-13T04:51:58.574Z"}
{"level":"info","message":"Server is listening on port 7000","timestamp":"2017-12-13T04:54:16.724Z"}
{"level":"info","message":"__ERROR_MIDDLEWARE__","timestamp":"2017-12-13T04:54:16.794Z"}
{"message":"body and content are required","stack":"BadRequestError: body and content are required\n    at Object.<anonymous>.starTrekEpisodesRouter.post (/home/cloud/Documents/codefellows/401/11-express-server/lab-jacob/route/star-trek-episodes-router.js:52:17)\n    at Layer.handle [as handle_request] (/home/cloud/Documents/codefellows/401/11-express-server/lab-jacob/node_modules/express/lib/router/layer.js:95:5)\n    at next (/home/cloud/Documents/codefellows/401/11-express-server/lab-jacob/node_modules/express/lib/router/route.js:137:13)\n    at /home/cloud/Documents/codefellows/401/11-express-server/lab-jacob/node_modules/body-parser/lib/read.js:130:5\n    at invokeCallback (/home/cloud/Documents/codefellows/401/11-express-server/lab-jacob/node_modules/raw-body/index.js:224:16)\n    at done (/home/cloud/Documents/codefellows/401/11-express-server/lab-jacob/node_modules/raw-body/index.js:213:7)\n    at IncomingMessage.onEnd (/home/cloud/Documents/codefellows/401/11-express-server/lab-jacob/node_modules/raw-body/index.js:273:7)\n    at emitNone (events.js:106:13)\n    at IncomingMessage.emit (events.js:208:7)\n    at endReadableNT (_stream_readable.js:1056:12)\n    at _combinedTickCallback (internal/process/next_tick.js:138:11)\n    at process._tickCallback (internal/process/next_tick.js:180:9)","name":"BadRequestError","level":"info","timestamp":"2017-12-13T04:54:16.794Z"}
{"level":"info","message":"Responding with a 400 status and message: body and content are required","timestamp":"2017-12-13T04:54:16.795Z"}
{"level":"info","message":"__ERROR_MIDDLEWARE__","timestamp":"2017-12-13T04:54:16.830Z"}
{"message":"Cast to ObjectId failed for value \"WRONG_ID\" at path \"_id\" for model \"episode\"","stack":"CastError: Cast to ObjectId failed for value \"WRONG_ID\" at path \"_id\" for model \"episode\"\n    at new CastError (/home/cloud/Documents/codefellows/401/11-express-server/lab-jacob/node_modules/mongoose/lib/error/cast.js:27:11)\n    at ObjectId.Object.<anonymous>.ObjectId.cast (/home/cloud/Documents/codefellows/401/11-express-server/lab-jacob/node_modules/mongoose/lib/schema/objectid.js:158:13)\n    at ObjectId.Object.<anonymous>.SchemaType._castForQuery (/home/cloud/Documents/codefellows/401/11-express-server/lab-jacob/node_modules/mongoose/lib/schematype.js:1088:15)\n    at ObjectId.Object.<anonymous>.ObjectId.castForQuery (/home/cloud/Documents/codefellows/401/11-express-server/lab-jacob/node_modules/mongoose/lib/schema/objectid.js:198:15)\n    at ObjectId.Object.<anonymous>.SchemaType.castForQueryWrapper (/home/cloud/Documents/codefellows/401/11-express-server/lab-jacob/node_modules/mongoose/lib/schematype.js:1045:15)\n    at cast (/home/cloud/Documents/codefellows/401/11-express-server/lab-jacob/node_modules/mongoose/lib/cast.js:269:32)\n    at model.Query.Object.<anonymous>.Query.cast (/home/cloud/Documents/codefellows/401/11-express-server/lab-jacob/node_modules/mongoose/lib/query.js:3302:12)\n    at model.Query.Object.<anonymous>.Query._castConditions (/home/cloud/Documents/codefellows/401/11-express-server/lab-jacob/node_modules/mongoose/lib/query.js:1292:10)\n    at model.Query.Object.<anonymous>.Query._findOne (/home/cloud/Documents/codefellows/401/11-express-server/lab-jacob/node_modules/mongoose/lib/query.js:1504:8)\n    at /home/cloud/Documents/codefellows/401/11-express-server/lab-jacob/node_modules/kareem/index.js:250:8\n    at /home/cloud/Documents/codefellows/401/11-express-server/lab-jacob/node_modules/kareem/index.js:23:7\n    at _combinedTickCallback (internal/process/next_tick.js:131:7)\n    at process._tickCallback (internal/process/next_tick.js:180:9)","name":"CastError","stringValue":"\"WRONG_ID\"","kind":"ObjectId","value":"WRONG_ID","path":"_id","level":"info","timestamp":"2017-12-13T04:54:16.830Z"}
{"level":"info","message":"Responding with a 404 status code","timestamp":"2017-12-13T04:54:16.831Z"}
{"level":"info","message":"Server off","timestamp":"2017-12-13T04:54:16.856Z"}
{"level":"info","message":"Server is listening on port 7000","timestamp":"2017-12-13T04:59:17.823Z"}
{"level":"info","message":"__ERROR_MIDDLEWARE__","timestamp":"2017-12-13T04:59:17.897Z"}
{"message":"body and content are required","stack":"BadRequestError: body and content are required\n    at Object.<anonymous>.starTrekEpisodesRouter.post (/home/cloud/Documents/codefellows/401/11-express-server/lab-jacob/route/star-trek-episodes-router.js:52:17)\n    at Layer.handle [as handle_request] (/home/cloud/Documents/codefellows/401/11-express-server/lab-jacob/node_modules/express/lib/router/layer.js:95:5)\n    at next (/home/cloud/Documents/codefellows/401/11-express-server/lab-jacob/node_modules/express/lib/router/route.js:137:13)\n    at /home/cloud/Documents/codefellows/401/11-express-server/lab-jacob/node_modules/body-parser/lib/read.js:130:5\n    at invokeCallback (/home/cloud/Documents/codefellows/401/11-express-server/lab-jacob/node_modules/raw-body/index.js:224:16)\n    at done (/home/cloud/Documents/codefellows/401/11-express-server/lab-jacob/node_modules/raw-body/index.js:213:7)\n    at IncomingMessage.onEnd (/home/cloud/Documents/codefellows/401/11-express-server/lab-jacob/node_modules/raw-body/index.js:273:7)\n    at emitNone (events.js:106:13)\n    at IncomingMessage.emit (events.js:208:7)\n    at endReadableNT (_stream_readable.js:1056:12)\n    at _combinedTickCallback (internal/process/next_tick.js:138:11)\n    at process._tickCallback (internal/process/next_tick.js:180:9)","name":"BadRequestError","level":"info","timestamp":"2017-12-13T04:59:17.897Z"}
{"level":"info","message":"Responding with a 400 status and message: body and content are required","timestamp":"2017-12-13T04:59:17.898Z"}
{"level":"info","message":"__ERROR_MIDDLEWARE__","timestamp":"2017-12-13T04:59:17.924Z"}
{"message":"Cast to ObjectId failed for value \"WRONG_ID\" at path \"_id\" for model \"episode\"","stack":"CastError: Cast to ObjectId failed for value \"WRONG_ID\" at path \"_id\" for model \"episode\"\n    at new CastError (/home/cloud/Documents/codefellows/401/11-express-server/lab-jacob/node_modules/mongoose/lib/error/cast.js:27:11)\n    at ObjectId.Object.<anonymous>.ObjectId.cast (/home/cloud/Documents/codefellows/401/11-express-server/lab-jacob/node_modules/mongoose/lib/schema/objectid.js:158:13)\n    at ObjectId.Object.<anonymous>.SchemaType._castForQuery (/home/cloud/Documents/codefellows/401/11-express-server/lab-jacob/node_modules/mongoose/lib/schematype.js:1088:15)\n    at ObjectId.Object.<anonymous>.ObjectId.castForQuery (/home/cloud/Documents/codefellows/401/11-express-server/lab-jacob/node_modules/mongoose/lib/schema/objectid.js:198:15)\n    at ObjectId.Object.<anonymous>.SchemaType.castForQueryWrapper (/home/cloud/Documents/codefellows/401/11-express-server/lab-jacob/node_modules/mongoose/lib/schematype.js:1045:15)\n    at cast (/home/cloud/Documents/codefellows/401/11-express-server/lab-jacob/node_modules/mongoose/lib/cast.js:269:32)\n    at model.Query.Object.<anonymous>.Query.cast (/home/cloud/Documents/codefellows/401/11-express-server/lab-jacob/node_modules/mongoose/lib/query.js:3302:12)\n    at model.Query.Object.<anonymous>.Query._castConditions (/home/cloud/Documents/codefellows/401/11-express-server/lab-jacob/node_modules/mongoose/lib/query.js:1292:10)\n    at model.Query.Object.<anonymous>.Query._findOne (/home/cloud/Documents/codefellows/401/11-express-server/lab-jacob/node_modules/mongoose/lib/query.js:1504:8)\n    at /home/cloud/Documents/codefellows/401/11-express-server/lab-jacob/node_modules/kareem/index.js:250:8\n    at /home/cloud/Documents/codefellows/401/11-express-server/lab-jacob/node_modules/kareem/index.js:23:7\n    at _combinedTickCallback (internal/process/next_tick.js:131:7)\n    at process._tickCallback (internal/process/next_tick.js:180:9)","name":"CastError","stringValue":"\"WRONG_ID\"","kind":"ObjectId","value":"WRONG_ID","path":"_id","level":"info","timestamp":"2017-12-13T04:59:17.924Z"}
{"level":"info","message":"Responding with a 404 status code","timestamp":"2017-12-13T04:59:17.925Z"}
{"level":"info","message":"Server off","timestamp":"2017-12-13T04:59:18.014Z"}
{"level":"info","message":"Server is listening on port 7000","timestamp":"2017-12-13T05:08:18.493Z"}
{"level":"info","message":"__ERROR_MIDDLEWARE__","timestamp":"2017-12-13T05:08:18.565Z"}
{"message":"body and content are required","stack":"BadRequestError: body and content are required\n    at Object.<anonymous>.starTrekEpisodesRouter.post (/home/cloud/Documents/codefellows/401/11-express-server/lab-jacob/route/star-trek-episodes-router.js:52:17)\n    at Layer.handle [as handle_request] (/home/cloud/Documents/codefellows/401/11-express-server/lab-jacob/node_modules/express/lib/router/layer.js:95:5)\n    at next (/home/cloud/Documents/codefellows/401/11-express-server/lab-jacob/node_modules/express/lib/router/route.js:137:13)\n    at /home/cloud/Documents/codefellows/401/11-express-server/lab-jacob/node_modules/body-parser/lib/read.js:130:5\n    at invokeCallback (/home/cloud/Documents/codefellows/401/11-express-server/lab-jacob/node_modules/raw-body/index.js:224:16)\n    at done (/home/cloud/Documents/codefellows/401/11-express-server/lab-jacob/node_modules/raw-body/index.js:213:7)\n    at IncomingMessage.onEnd (/home/cloud/Documents/codefellows/401/11-express-server/lab-jacob/node_modules/raw-body/index.js:273:7)\n    at emitNone (events.js:106:13)\n    at IncomingMessage.emit (events.js:208:7)\n    at endReadableNT (_stream_readable.js:1056:12)\n    at _combinedTickCallback (internal/process/next_tick.js:138:11)\n    at process._tickCallback (internal/process/next_tick.js:180:9)","name":"BadRequestError","level":"info","timestamp":"2017-12-13T05:08:18.566Z"}
{"level":"info","message":"Responding with a 400 status and message: body and content are required","timestamp":"2017-12-13T05:08:18.566Z"}
{"level":"info","message":"__ERROR_MIDDLEWARE__","timestamp":"2017-12-13T05:08:18.575Z"}
{"message":"Cast to ObjectId failed for value \"WRONG_ID\" at path \"_id\" for model \"episode\"","stack":"CastError: Cast to ObjectId failed for value \"WRONG_ID\" at path \"_id\" for model \"episode\"\n    at new CastError (/home/cloud/Documents/codefellows/401/11-express-server/lab-jacob/node_modules/mongoose/lib/error/cast.js:27:11)\n    at ObjectId.Object.<anonymous>.ObjectId.cast (/home/cloud/Documents/codefellows/401/11-express-server/lab-jacob/node_modules/mongoose/lib/schema/objectid.js:158:13)\n    at ObjectId.Object.<anonymous>.SchemaType._castForQuery (/home/cloud/Documents/codefellows/401/11-express-server/lab-jacob/node_modules/mongoose/lib/schematype.js:1088:15)\n    at ObjectId.Object.<anonymous>.ObjectId.castForQuery (/home/cloud/Documents/codefellows/401/11-express-server/lab-jacob/node_modules/mongoose/lib/schema/objectid.js:198:15)\n    at ObjectId.Object.<anonymous>.SchemaType.castForQueryWrapper (/home/cloud/Documents/codefellows/401/11-express-server/lab-jacob/node_modules/mongoose/lib/schematype.js:1045:15)\n    at cast (/home/cloud/Documents/codefellows/401/11-express-server/lab-jacob/node_modules/mongoose/lib/cast.js:269:32)\n    at model.Query.Object.<anonymous>.Query.cast (/home/cloud/Documents/codefellows/401/11-express-server/lab-jacob/node_modules/mongoose/lib/query.js:3302:12)\n    at model.Query.Object.<anonymous>.Query._castConditions (/home/cloud/Documents/codefellows/401/11-express-server/lab-jacob/node_modules/mongoose/lib/query.js:1292:10)\n    at model.Query.Object.<anonymous>.Query._findOne (/home/cloud/Documents/codefellows/401/11-express-server/lab-jacob/node_modules/mongoose/lib/query.js:1504:8)\n    at /home/cloud/Documents/codefellows/401/11-express-server/lab-jacob/node_modules/kareem/index.js:250:8\n    at /home/cloud/Documents/codefellows/401/11-express-server/lab-jacob/node_modules/kareem/index.js:23:7\n    at _combinedTickCallback (internal/process/next_tick.js:131:7)\n    at process._tickCallback (internal/process/next_tick.js:180:9)","name":"CastError","stringValue":"\"WRONG_ID\"","kind":"ObjectId","value":"WRONG_ID","path":"_id","level":"info","timestamp":"2017-12-13T05:08:18.575Z"}
{"level":"info","message":"Responding with a 404 status code","timestamp":"2017-12-13T05:08:18.576Z"}
{"level":"info","message":"Server off","timestamp":"2017-12-13T05:08:18.580Z"}
{"level":"info","message":"Server is listening on port 7000","timestamp":"2017-12-13T05:12:47.963Z"}
{"level":"info","message":"__ERROR_MIDDLEWARE__","timestamp":"2017-12-13T05:12:48.036Z"}
{"message":"body and content are required","stack":"BadRequestError: body and content are required\n    at Object.<anonymous>.starTrekEpisodesRouter.post (/home/cloud/Documents/codefellows/401/11-express-server/lab-jacob/route/star-trek-episodes-router.js:52:17)\n    at Layer.handle [as handle_request] (/home/cloud/Documents/codefellows/401/11-express-server/lab-jacob/node_modules/express/lib/router/layer.js:95:5)\n    at next (/home/cloud/Documents/codefellows/401/11-express-server/lab-jacob/node_modules/express/lib/router/route.js:137:13)\n    at /home/cloud/Documents/codefellows/401/11-express-server/lab-jacob/node_modules/body-parser/lib/read.js:130:5\n    at invokeCallback (/home/cloud/Documents/codefellows/401/11-express-server/lab-jacob/node_modules/raw-body/index.js:224:16)\n    at done (/home/cloud/Documents/codefellows/401/11-express-server/lab-jacob/node_modules/raw-body/index.js:213:7)\n    at IncomingMessage.onEnd (/home/cloud/Documents/codefellows/401/11-express-server/lab-jacob/node_modules/raw-body/index.js:273:7)\n    at emitNone (events.js:106:13)\n    at IncomingMessage.emit (events.js:208:7)\n    at endReadableNT (_stream_readable.js:1056:12)\n    at _combinedTickCallback (internal/process/next_tick.js:138:11)\n    at process._tickCallback (internal/process/next_tick.js:180:9)","name":"BadRequestError","level":"info","timestamp":"2017-12-13T05:12:48.036Z"}
{"level":"info","message":"Responding with a 400 status and message: body and content are required","timestamp":"2017-12-13T05:12:48.036Z"}
{"level":"info","message":"__ERROR_MIDDLEWARE__","timestamp":"2017-12-13T05:12:48.062Z"}
{"message":"Cast to ObjectId failed for value \"WRONG_ID\" at path \"_id\" for model \"episode\"","stack":"CastError: Cast to ObjectId failed for value \"WRONG_ID\" at path \"_id\" for model \"episode\"\n    at new CastError (/home/cloud/Documents/codefellows/401/11-express-server/lab-jacob/node_modules/mongoose/lib/error/cast.js:27:11)\n    at ObjectId.Object.<anonymous>.ObjectId.cast (/home/cloud/Documents/codefellows/401/11-express-server/lab-jacob/node_modules/mongoose/lib/schema/objectid.js:158:13)\n    at ObjectId.Object.<anonymous>.SchemaType._castForQuery (/home/cloud/Documents/codefellows/401/11-express-server/lab-jacob/node_modules/mongoose/lib/schematype.js:1088:15)\n    at ObjectId.Object.<anonymous>.ObjectId.castForQuery (/home/cloud/Documents/codefellows/401/11-express-server/lab-jacob/node_modules/mongoose/lib/schema/objectid.js:198:15)\n    at ObjectId.Object.<anonymous>.SchemaType.castForQueryWrapper (/home/cloud/Documents/codefellows/401/11-express-server/lab-jacob/node_modules/mongoose/lib/schematype.js:1045:15)\n    at cast (/home/cloud/Documents/codefellows/401/11-express-server/lab-jacob/node_modules/mongoose/lib/cast.js:269:32)\n    at model.Query.Object.<anonymous>.Query.cast (/home/cloud/Documents/codefellows/401/11-express-server/lab-jacob/node_modules/mongoose/lib/query.js:3302:12)\n    at model.Query.Object.<anonymous>.Query._castConditions (/home/cloud/Documents/codefellows/401/11-express-server/lab-jacob/node_modules/mongoose/lib/query.js:1292:10)\n    at model.Query.Object.<anonymous>.Query._findOne (/home/cloud/Documents/codefellows/401/11-express-server/lab-jacob/node_modules/mongoose/lib/query.js:1504:8)\n    at /home/cloud/Documents/codefellows/401/11-express-server/lab-jacob/node_modules/kareem/index.js:250:8\n    at /home/cloud/Documents/codefellows/401/11-express-server/lab-jacob/node_modules/kareem/index.js:23:7\n    at _combinedTickCallback (internal/process/next_tick.js:131:7)\n    at process._tickCallback (internal/process/next_tick.js:180:9)","name":"CastError","stringValue":"\"WRONG_ID\"","kind":"ObjectId","value":"WRONG_ID","path":"_id","level":"info","timestamp":"2017-12-13T05:12:48.063Z"}
{"level":"info","message":"Responding with a 404 status code","timestamp":"2017-12-13T05:12:48.063Z"}
{"level":"info","message":"Server off","timestamp":"2017-12-13T05:12:48.149Z"}
{"level":"info","message":"Server is listening on port 7000","timestamp":"2017-12-13T05:16:35.846Z"}
{"level":"info","message":"__ERROR_MIDDLEWARE__","timestamp":"2017-12-13T05:16:35.915Z"}
{"message":"body and content are required","stack":"BadRequestError: body and content are required\n    at Object.<anonymous>.starTrekEpisodesRouter.post (/home/cloud/Documents/codefellows/401/11-express-server/lab-jacob/route/star-trek-episodes-router.js:52:17)\n    at Layer.handle [as handle_request] (/home/cloud/Documents/codefellows/401/11-express-server/lab-jacob/node_modules/express/lib/router/layer.js:95:5)\n    at next (/home/cloud/Documents/codefellows/401/11-express-server/lab-jacob/node_modules/express/lib/router/route.js:137:13)\n    at /home/cloud/Documents/codefellows/401/11-express-server/lab-jacob/node_modules/body-parser/lib/read.js:130:5\n    at invokeCallback (/home/cloud/Documents/codefellows/401/11-express-server/lab-jacob/node_modules/raw-body/index.js:224:16)\n    at done (/home/cloud/Documents/codefellows/401/11-express-server/lab-jacob/node_modules/raw-body/index.js:213:7)\n    at IncomingMessage.onEnd (/home/cloud/Documents/codefellows/401/11-express-server/lab-jacob/node_modules/raw-body/index.js:273:7)\n    at emitNone (events.js:106:13)\n    at IncomingMessage.emit (events.js:208:7)\n    at endReadableNT (_stream_readable.js:1056:12)\n    at _combinedTickCallback (internal/process/next_tick.js:138:11)\n    at process._tickCallback (internal/process/next_tick.js:180:9)","name":"BadRequestError","level":"info","timestamp":"2017-12-13T05:16:35.915Z"}
{"level":"info","message":"Responding with a 400 status and message: body and content are required","timestamp":"2017-12-13T05:16:35.916Z"}
{"level":"info","message":"__ERROR_MIDDLEWARE__","timestamp":"2017-12-13T05:16:35.942Z"}
{"message":"Cast to ObjectId failed for value \"WRONG_ID\" at path \"_id\" for model \"episode\"","stack":"CastError: Cast to ObjectId failed for value \"WRONG_ID\" at path \"_id\" for model \"episode\"\n    at new CastError (/home/cloud/Documents/codefellows/401/11-express-server/lab-jacob/node_modules/mongoose/lib/error/cast.js:27:11)\n    at ObjectId.Object.<anonymous>.ObjectId.cast (/home/cloud/Documents/codefellows/401/11-express-server/lab-jacob/node_modules/mongoose/lib/schema/objectid.js:158:13)\n    at ObjectId.Object.<anonymous>.SchemaType._castForQuery (/home/cloud/Documents/codefellows/401/11-express-server/lab-jacob/node_modules/mongoose/lib/schematype.js:1088:15)\n    at ObjectId.Object.<anonymous>.ObjectId.castForQuery (/home/cloud/Documents/codefellows/401/11-express-server/lab-jacob/node_modules/mongoose/lib/schema/objectid.js:198:15)\n    at ObjectId.Object.<anonymous>.SchemaType.castForQueryWrapper (/home/cloud/Documents/codefellows/401/11-express-server/lab-jacob/node_modules/mongoose/lib/schematype.js:1045:15)\n    at cast (/home/cloud/Documents/codefellows/401/11-express-server/lab-jacob/node_modules/mongoose/lib/cast.js:269:32)\n    at model.Query.Object.<anonymous>.Query.cast (/home/cloud/Documents/codefellows/401/11-express-server/lab-jacob/node_modules/mongoose/lib/query.js:3302:12)\n    at model.Query.Object.<anonymous>.Query._castConditions (/home/cloud/Documents/codefellows/401/11-express-server/lab-jacob/node_modules/mongoose/lib/query.js:1292:10)\n    at model.Query.Object.<anonymous>.Query._findOne (/home/cloud/Documents/codefellows/401/11-express-server/lab-jacob/node_modules/mongoose/lib/query.js:1504:8)\n    at /home/cloud/Documents/codefellows/401/11-express-server/lab-jacob/node_modules/kareem/index.js:250:8\n    at /home/cloud/Documents/codefellows/401/11-express-server/lab-jacob/node_modules/kareem/index.js:23:7\n    at _combinedTickCallback (internal/process/next_tick.js:131:7)\n    at process._tickCallback (internal/process/next_tick.js:180:9)","name":"CastError","stringValue":"\"WRONG_ID\"","kind":"ObjectId","value":"WRONG_ID","path":"_id","level":"info","timestamp":"2017-12-13T05:16:35.943Z"}
{"level":"info","message":"Responding with a 404 status code","timestamp":"2017-12-13T05:16:35.943Z"}
{"level":"info","message":"Server off","timestamp":"2017-12-13T05:16:36.040Z"}
{"level":"info","message":"Server is listening on port 7000","timestamp":"2017-12-13T05:17:04.324Z"}
{"level":"info","message":"__ERROR_MIDDLEWARE__","timestamp":"2017-12-13T05:17:04.397Z"}
{"message":"body and content are required","stack":"BadRequestError: body and content are required\n    at Object.<anonymous>.starTrekEpisodesRouter.post (/home/cloud/Documents/codefellows/401/11-express-server/lab-jacob/route/star-trek-episodes-router.js:52:17)\n    at Layer.handle [as handle_request] (/home/cloud/Documents/codefellows/401/11-express-server/lab-jacob/node_modules/express/lib/router/layer.js:95:5)\n    at next (/home/cloud/Documents/codefellows/401/11-express-server/lab-jacob/node_modules/express/lib/router/route.js:137:13)\n    at /home/cloud/Documents/codefellows/401/11-express-server/lab-jacob/node_modules/body-parser/lib/read.js:130:5\n    at invokeCallback (/home/cloud/Documents/codefellows/401/11-express-server/lab-jacob/node_modules/raw-body/index.js:224:16)\n    at done (/home/cloud/Documents/codefellows/401/11-express-server/lab-jacob/node_modules/raw-body/index.js:213:7)\n    at IncomingMessage.onEnd (/home/cloud/Documents/codefellows/401/11-express-server/lab-jacob/node_modules/raw-body/index.js:273:7)\n    at emitNone (events.js:106:13)\n    at IncomingMessage.emit (events.js:208:7)\n    at endReadableNT (_stream_readable.js:1056:12)\n    at _combinedTickCallback (internal/process/next_tick.js:138:11)\n    at process._tickCallback (internal/process/next_tick.js:180:9)","name":"BadRequestError","level":"info","timestamp":"2017-12-13T05:17:04.398Z"}
{"level":"info","message":"Responding with a 400 status and message: body and content are required","timestamp":"2017-12-13T05:17:04.398Z"}
{"level":"info","message":"__ERROR_MIDDLEWARE__","timestamp":"2017-12-13T05:17:04.425Z"}
{"message":"Cast to ObjectId failed for value \"WRONG_ID\" at path \"_id\" for model \"episode\"","stack":"CastError: Cast to ObjectId failed for value \"WRONG_ID\" at path \"_id\" for model \"episode\"\n    at new CastError (/home/cloud/Documents/codefellows/401/11-express-server/lab-jacob/node_modules/mongoose/lib/error/cast.js:27:11)\n    at ObjectId.Object.<anonymous>.ObjectId.cast (/home/cloud/Documents/codefellows/401/11-express-server/lab-jacob/node_modules/mongoose/lib/schema/objectid.js:158:13)\n    at ObjectId.Object.<anonymous>.SchemaType._castForQuery (/home/cloud/Documents/codefellows/401/11-express-server/lab-jacob/node_modules/mongoose/lib/schematype.js:1088:15)\n    at ObjectId.Object.<anonymous>.ObjectId.castForQuery (/home/cloud/Documents/codefellows/401/11-express-server/lab-jacob/node_modules/mongoose/lib/schema/objectid.js:198:15)\n    at ObjectId.Object.<anonymous>.SchemaType.castForQueryWrapper (/home/cloud/Documents/codefellows/401/11-express-server/lab-jacob/node_modules/mongoose/lib/schematype.js:1045:15)\n    at cast (/home/cloud/Documents/codefellows/401/11-express-server/lab-jacob/node_modules/mongoose/lib/cast.js:269:32)\n    at model.Query.Object.<anonymous>.Query.cast (/home/cloud/Documents/codefellows/401/11-express-server/lab-jacob/node_modules/mongoose/lib/query.js:3302:12)\n    at model.Query.Object.<anonymous>.Query._castConditions (/home/cloud/Documents/codefellows/401/11-express-server/lab-jacob/node_modules/mongoose/lib/query.js:1292:10)\n    at model.Query.Object.<anonymous>.Query._findOne (/home/cloud/Documents/codefellows/401/11-express-server/lab-jacob/node_modules/mongoose/lib/query.js:1504:8)\n    at /home/cloud/Documents/codefellows/401/11-express-server/lab-jacob/node_modules/kareem/index.js:250:8\n    at /home/cloud/Documents/codefellows/401/11-express-server/lab-jacob/node_modules/kareem/index.js:23:7\n    at _combinedTickCallback (internal/process/next_tick.js:131:7)\n    at process._tickCallback (internal/process/next_tick.js:180:9)","name":"CastError","stringValue":"\"WRONG_ID\"","kind":"ObjectId","value":"WRONG_ID","path":"_id","level":"info","timestamp":"2017-12-13T05:17:04.425Z"}
{"level":"info","message":"Responding with a 404 status code","timestamp":"2017-12-13T05:17:04.426Z"}
{"level":"info","message":"Server off","timestamp":"2017-12-13T05:17:04.513Z"}
{"level":"info","message":"Server is listening on port 7000","timestamp":"2017-12-13T05:17:29.059Z"}
{"level":"info","message":"__ERROR_MIDDLEWARE__","timestamp":"2017-12-13T05:17:29.133Z"}
{"message":"body and content are required","stack":"BadRequestError: body and content are required\n    at Object.<anonymous>.starTrekEpisodesRouter.post (/home/cloud/Documents/codefellows/401/11-express-server/lab-jacob/route/star-trek-episodes-router.js:52:17)\n    at Layer.handle [as handle_request] (/home/cloud/Documents/codefellows/401/11-express-server/lab-jacob/node_modules/express/lib/router/layer.js:95:5)\n    at next (/home/cloud/Documents/codefellows/401/11-express-server/lab-jacob/node_modules/express/lib/router/route.js:137:13)\n    at /home/cloud/Documents/codefellows/401/11-express-server/lab-jacob/node_modules/body-parser/lib/read.js:130:5\n    at invokeCallback (/home/cloud/Documents/codefellows/401/11-express-server/lab-jacob/node_modules/raw-body/index.js:224:16)\n    at done (/home/cloud/Documents/codefellows/401/11-express-server/lab-jacob/node_modules/raw-body/index.js:213:7)\n    at IncomingMessage.onEnd (/home/cloud/Documents/codefellows/401/11-express-server/lab-jacob/node_modules/raw-body/index.js:273:7)\n    at emitNone (events.js:106:13)\n    at IncomingMessage.emit (events.js:208:7)\n    at endReadableNT (_stream_readable.js:1056:12)\n    at _combinedTickCallback (internal/process/next_tick.js:138:11)\n    at process._tickCallback (internal/process/next_tick.js:180:9)","name":"BadRequestError","level":"info","timestamp":"2017-12-13T05:17:29.134Z"}
{"level":"info","message":"Responding with a 400 status and message: body and content are required","timestamp":"2017-12-13T05:17:29.134Z"}
{"level":"info","message":"__ERROR_MIDDLEWARE__","timestamp":"2017-12-13T05:17:29.169Z"}
{"message":"Cast to ObjectId failed for value \"WRONG_ID\" at path \"_id\" for model \"episode\"","stack":"CastError: Cast to ObjectId failed for value \"WRONG_ID\" at path \"_id\" for model \"episode\"\n    at new CastError (/home/cloud/Documents/codefellows/401/11-express-server/lab-jacob/node_modules/mongoose/lib/error/cast.js:27:11)\n    at ObjectId.Object.<anonymous>.ObjectId.cast (/home/cloud/Documents/codefellows/401/11-express-server/lab-jacob/node_modules/mongoose/lib/schema/objectid.js:158:13)\n    at ObjectId.Object.<anonymous>.SchemaType._castForQuery (/home/cloud/Documents/codefellows/401/11-express-server/lab-jacob/node_modules/mongoose/lib/schematype.js:1088:15)\n    at ObjectId.Object.<anonymous>.ObjectId.castForQuery (/home/cloud/Documents/codefellows/401/11-express-server/lab-jacob/node_modules/mongoose/lib/schema/objectid.js:198:15)\n    at ObjectId.Object.<anonymous>.SchemaType.castForQueryWrapper (/home/cloud/Documents/codefellows/401/11-express-server/lab-jacob/node_modules/mongoose/lib/schematype.js:1045:15)\n    at cast (/home/cloud/Documents/codefellows/401/11-express-server/lab-jacob/node_modules/mongoose/lib/cast.js:269:32)\n    at model.Query.Object.<anonymous>.Query.cast (/home/cloud/Documents/codefellows/401/11-express-server/lab-jacob/node_modules/mongoose/lib/query.js:3302:12)\n    at model.Query.Object.<anonymous>.Query._castConditions (/home/cloud/Documents/codefellows/401/11-express-server/lab-jacob/node_modules/mongoose/lib/query.js:1292:10)\n    at model.Query.Object.<anonymous>.Query._findOne (/home/cloud/Documents/codefellows/401/11-express-server/lab-jacob/node_modules/mongoose/lib/query.js:1504:8)\n    at /home/cloud/Documents/codefellows/401/11-express-server/lab-jacob/node_modules/kareem/index.js:250:8\n    at /home/cloud/Documents/codefellows/401/11-express-server/lab-jacob/node_modules/kareem/index.js:23:7\n    at _combinedTickCallback (internal/process/next_tick.js:131:7)\n    at process._tickCallback (internal/process/next_tick.js:180:9)","name":"CastError","stringValue":"\"WRONG_ID\"","kind":"ObjectId","value":"WRONG_ID","path":"_id","level":"info","timestamp":"2017-12-13T05:17:29.169Z"}
{"level":"info","message":"Responding with a 404 status code","timestamp":"2017-12-13T05:17:29.170Z"}
{"level":"info","message":"Server off","timestamp":"2017-12-13T05:17:29.259Z"}
{"level":"info","message":"Server is listening on port 7000","timestamp":"2017-12-13T05:20:54.640Z"}
{"level":"info","message":"__ERROR_MIDDLEWARE__","timestamp":"2017-12-13T05:20:54.715Z"}
{"message":"body and content are required","stack":"BadRequestError: body and content are required\n    at Object.<anonymous>.starTrekEpisodesRouter.post (/home/cloud/Documents/codefellows/401/11-express-server/lab-jacob/route/star-trek-episodes-router.js:52:17)\n    at Layer.handle [as handle_request] (/home/cloud/Documents/codefellows/401/11-express-server/lab-jacob/node_modules/express/lib/router/layer.js:95:5)\n    at next (/home/cloud/Documents/codefellows/401/11-express-server/lab-jacob/node_modules/express/lib/router/route.js:137:13)\n    at /home/cloud/Documents/codefellows/401/11-express-server/lab-jacob/node_modules/body-parser/lib/read.js:130:5\n    at invokeCallback (/home/cloud/Documents/codefellows/401/11-express-server/lab-jacob/node_modules/raw-body/index.js:224:16)\n    at done (/home/cloud/Documents/codefellows/401/11-express-server/lab-jacob/node_modules/raw-body/index.js:213:7)\n    at IncomingMessage.onEnd (/home/cloud/Documents/codefellows/401/11-express-server/lab-jacob/node_modules/raw-body/index.js:273:7)\n    at emitNone (events.js:106:13)\n    at IncomingMessage.emit (events.js:208:7)\n    at endReadableNT (_stream_readable.js:1056:12)\n    at _combinedTickCallback (internal/process/next_tick.js:138:11)\n    at process._tickCallback (internal/process/next_tick.js:180:9)","name":"BadRequestError","level":"info","timestamp":"2017-12-13T05:20:54.715Z"}
{"level":"info","message":"Responding with a 400 status and message: body and content are required","timestamp":"2017-12-13T05:20:54.716Z"}
{"level":"info","message":"__ERROR_MIDDLEWARE__","timestamp":"2017-12-13T05:20:54.742Z"}
{"message":"Cast to ObjectId failed for value \"WRONG_ID\" at path \"_id\" for model \"episode\"","stack":"CastError: Cast to ObjectId failed for value \"WRONG_ID\" at path \"_id\" for model \"episode\"\n    at new CastError (/home/cloud/Documents/codefellows/401/11-express-server/lab-jacob/node_modules/mongoose/lib/error/cast.js:27:11)\n    at ObjectId.Object.<anonymous>.ObjectId.cast (/home/cloud/Documents/codefellows/401/11-express-server/lab-jacob/node_modules/mongoose/lib/schema/objectid.js:158:13)\n    at ObjectId.Object.<anonymous>.SchemaType._castForQuery (/home/cloud/Documents/codefellows/401/11-express-server/lab-jacob/node_modules/mongoose/lib/schematype.js:1088:15)\n    at ObjectId.Object.<anonymous>.ObjectId.castForQuery (/home/cloud/Documents/codefellows/401/11-express-server/lab-jacob/node_modules/mongoose/lib/schema/objectid.js:198:15)\n    at ObjectId.Object.<anonymous>.SchemaType.castForQueryWrapper (/home/cloud/Documents/codefellows/401/11-express-server/lab-jacob/node_modules/mongoose/lib/schematype.js:1045:15)\n    at cast (/home/cloud/Documents/codefellows/401/11-express-server/lab-jacob/node_modules/mongoose/lib/cast.js:269:32)\n    at model.Query.Object.<anonymous>.Query.cast (/home/cloud/Documents/codefellows/401/11-express-server/lab-jacob/node_modules/mongoose/lib/query.js:3302:12)\n    at model.Query.Object.<anonymous>.Query._castConditions (/home/cloud/Documents/codefellows/401/11-express-server/lab-jacob/node_modules/mongoose/lib/query.js:1292:10)\n    at model.Query.Object.<anonymous>.Query._findOne (/home/cloud/Documents/codefellows/401/11-express-server/lab-jacob/node_modules/mongoose/lib/query.js:1504:8)\n    at /home/cloud/Documents/codefellows/401/11-express-server/lab-jacob/node_modules/kareem/index.js:250:8\n    at /home/cloud/Documents/codefellows/401/11-express-server/lab-jacob/node_modules/kareem/index.js:23:7\n    at _combinedTickCallback (internal/process/next_tick.js:131:7)\n    at process._tickCallback (internal/process/next_tick.js:180:9)","name":"CastError","stringValue":"\"WRONG_ID\"","kind":"ObjectId","value":"WRONG_ID","path":"_id","level":"info","timestamp":"2017-12-13T05:20:54.742Z"}
{"level":"info","message":"Responding with a 404 status code","timestamp":"2017-12-13T05:20:54.743Z"}
{"level":"info","message":"Server off","timestamp":"2017-12-13T05:20:54.831Z"}
{"level":"info","message":"Server is listening on port 7000","timestamp":"2017-12-13T05:28:53.007Z"}
{"level":"info","message":"__ERROR_MIDDLEWARE__","timestamp":"2017-12-13T05:28:53.080Z"}
{"message":"body and content are required","stack":"BadRequestError: body and content are required\n    at Object.<anonymous>.starTrekEpisodesRouter.post (/home/cloud/Documents/codefellows/401/11-express-server/lab-jacob/route/star-trek-episodes-router.js:52:17)\n    at Layer.handle [as handle_request] (/home/cloud/Documents/codefellows/401/11-express-server/lab-jacob/node_modules/express/lib/router/layer.js:95:5)\n    at next (/home/cloud/Documents/codefellows/401/11-express-server/lab-jacob/node_modules/express/lib/router/route.js:137:13)\n    at /home/cloud/Documents/codefellows/401/11-express-server/lab-jacob/node_modules/body-parser/lib/read.js:130:5\n    at invokeCallback (/home/cloud/Documents/codefellows/401/11-express-server/lab-jacob/node_modules/raw-body/index.js:224:16)\n    at done (/home/cloud/Documents/codefellows/401/11-express-server/lab-jacob/node_modules/raw-body/index.js:213:7)\n    at IncomingMessage.onEnd (/home/cloud/Documents/codefellows/401/11-express-server/lab-jacob/node_modules/raw-body/index.js:273:7)\n    at emitNone (events.js:106:13)\n    at IncomingMessage.emit (events.js:208:7)\n    at endReadableNT (_stream_readable.js:1056:12)\n    at _combinedTickCallback (internal/process/next_tick.js:138:11)\n    at process._tickCallback (internal/process/next_tick.js:180:9)","name":"BadRequestError","level":"info","timestamp":"2017-12-13T05:28:53.080Z"}
{"level":"info","message":"Responding with a 400 status and message: body and content are required","timestamp":"2017-12-13T05:28:53.081Z"}
{"level":"info","message":"__ERROR_MIDDLEWARE__","timestamp":"2017-12-13T05:28:53.108Z"}
{"message":"Cast to ObjectId failed for value \"WRONG_ID\" at path \"_id\" for model \"episode\"","stack":"CastError: Cast to ObjectId failed for value \"WRONG_ID\" at path \"_id\" for model \"episode\"\n    at new CastError (/home/cloud/Documents/codefellows/401/11-express-server/lab-jacob/node_modules/mongoose/lib/error/cast.js:27:11)\n    at ObjectId.Object.<anonymous>.ObjectId.cast (/home/cloud/Documents/codefellows/401/11-express-server/lab-jacob/node_modules/mongoose/lib/schema/objectid.js:158:13)\n    at ObjectId.Object.<anonymous>.SchemaType._castForQuery (/home/cloud/Documents/codefellows/401/11-express-server/lab-jacob/node_modules/mongoose/lib/schematype.js:1088:15)\n    at ObjectId.Object.<anonymous>.ObjectId.castForQuery (/home/cloud/Documents/codefellows/401/11-express-server/lab-jacob/node_modules/mongoose/lib/schema/objectid.js:198:15)\n    at ObjectId.Object.<anonymous>.SchemaType.castForQueryWrapper (/home/cloud/Documents/codefellows/401/11-express-server/lab-jacob/node_modules/mongoose/lib/schematype.js:1045:15)\n    at cast (/home/cloud/Documents/codefellows/401/11-express-server/lab-jacob/node_modules/mongoose/lib/cast.js:269:32)\n    at model.Query.Object.<anonymous>.Query.cast (/home/cloud/Documents/codefellows/401/11-express-server/lab-jacob/node_modules/mongoose/lib/query.js:3302:12)\n    at model.Query.Object.<anonymous>.Query._castConditions (/home/cloud/Documents/codefellows/401/11-express-server/lab-jacob/node_modules/mongoose/lib/query.js:1292:10)\n    at model.Query.Object.<anonymous>.Query._findOne (/home/cloud/Documents/codefellows/401/11-express-server/lab-jacob/node_modules/mongoose/lib/query.js:1504:8)\n    at /home/cloud/Documents/codefellows/401/11-express-server/lab-jacob/node_modules/kareem/index.js:250:8\n    at /home/cloud/Documents/codefellows/401/11-express-server/lab-jacob/node_modules/kareem/index.js:23:7\n    at _combinedTickCallback (internal/process/next_tick.js:131:7)\n    at process._tickCallback (internal/process/next_tick.js:180:9)","name":"CastError","stringValue":"\"WRONG_ID\"","kind":"ObjectId","value":"WRONG_ID","path":"_id","level":"info","timestamp":"2017-12-13T05:28:53.108Z"}
{"level":"info","message":"Responding with a 404 status code","timestamp":"2017-12-13T05:28:53.108Z"}
{"level":"info","message":"Server off","timestamp":"2017-12-13T05:28:53.197Z"}
{"level":"info","message":"Server is listening on port 7000","timestamp":"2017-12-13T05:30:11.244Z"}
{"level":"info","message":"__ERROR_MIDDLEWARE__","timestamp":"2017-12-13T05:30:11.315Z"}
{"message":"body and content are required","stack":"BadRequestError: body and content are required\n    at Object.<anonymous>.starTrekEpisodesRouter.post (/home/cloud/Documents/codefellows/401/11-express-server/lab-jacob/route/star-trek-episodes-router.js:52:17)\n    at Layer.handle [as handle_request] (/home/cloud/Documents/codefellows/401/11-express-server/lab-jacob/node_modules/express/lib/router/layer.js:95:5)\n    at next (/home/cloud/Documents/codefellows/401/11-express-server/lab-jacob/node_modules/express/lib/router/route.js:137:13)\n    at /home/cloud/Documents/codefellows/401/11-express-server/lab-jacob/node_modules/body-parser/lib/read.js:130:5\n    at invokeCallback (/home/cloud/Documents/codefellows/401/11-express-server/lab-jacob/node_modules/raw-body/index.js:224:16)\n    at done (/home/cloud/Documents/codefellows/401/11-express-server/lab-jacob/node_modules/raw-body/index.js:213:7)\n    at IncomingMessage.onEnd (/home/cloud/Documents/codefellows/401/11-express-server/lab-jacob/node_modules/raw-body/index.js:273:7)\n    at emitNone (events.js:106:13)\n    at IncomingMessage.emit (events.js:208:7)\n    at endReadableNT (_stream_readable.js:1056:12)\n    at _combinedTickCallback (internal/process/next_tick.js:138:11)\n    at process._tickCallback (internal/process/next_tick.js:180:9)","name":"BadRequestError","level":"info","timestamp":"2017-12-13T05:30:11.315Z"}
{"level":"info","message":"Responding with a 400 status and message: body and content are required","timestamp":"2017-12-13T05:30:11.316Z"}
{"level":"info","message":"__ERROR_MIDDLEWARE__","timestamp":"2017-12-13T05:30:11.344Z"}
{"message":"Cast to ObjectId failed for value \"WRONG_ID\" at path \"_id\" for model \"episode\"","stack":"CastError: Cast to ObjectId failed for value \"WRONG_ID\" at path \"_id\" for model \"episode\"\n    at new CastError (/home/cloud/Documents/codefellows/401/11-express-server/lab-jacob/node_modules/mongoose/lib/error/cast.js:27:11)\n    at ObjectId.Object.<anonymous>.ObjectId.cast (/home/cloud/Documents/codefellows/401/11-express-server/lab-jacob/node_modules/mongoose/lib/schema/objectid.js:158:13)\n    at ObjectId.Object.<anonymous>.SchemaType._castForQuery (/home/cloud/Documents/codefellows/401/11-express-server/lab-jacob/node_modules/mongoose/lib/schematype.js:1088:15)\n    at ObjectId.Object.<anonymous>.ObjectId.castForQuery (/home/cloud/Documents/codefellows/401/11-express-server/lab-jacob/node_modules/mongoose/lib/schema/objectid.js:198:15)\n    at ObjectId.Object.<anonymous>.SchemaType.castForQueryWrapper (/home/cloud/Documents/codefellows/401/11-express-server/lab-jacob/node_modules/mongoose/lib/schematype.js:1045:15)\n    at cast (/home/cloud/Documents/codefellows/401/11-express-server/lab-jacob/node_modules/mongoose/lib/cast.js:269:32)\n    at model.Query.Object.<anonymous>.Query.cast (/home/cloud/Documents/codefellows/401/11-express-server/lab-jacob/node_modules/mongoose/lib/query.js:3302:12)\n    at model.Query.Object.<anonymous>.Query._castConditions (/home/cloud/Documents/codefellows/401/11-express-server/lab-jacob/node_modules/mongoose/lib/query.js:1292:10)\n    at model.Query.Object.<anonymous>.Query._findOne (/home/cloud/Documents/codefellows/401/11-express-server/lab-jacob/node_modules/mongoose/lib/query.js:1504:8)\n    at /home/cloud/Documents/codefellows/401/11-express-server/lab-jacob/node_modules/kareem/index.js:250:8\n    at /home/cloud/Documents/codefellows/401/11-express-server/lab-jacob/node_modules/kareem/index.js:23:7\n    at _combinedTickCallback (internal/process/next_tick.js:131:7)\n    at process._tickCallback (internal/process/next_tick.js:180:9)","name":"CastError","stringValue":"\"WRONG_ID\"","kind":"ObjectId","value":"WRONG_ID","path":"_id","level":"info","timestamp":"2017-12-13T05:30:11.344Z"}
{"level":"info","message":"Responding with a 404 status code","timestamp":"2017-12-13T05:30:11.345Z"}
{"level":"info","message":"Server off","timestamp":"2017-12-13T05:30:11.432Z"}
{"level":"info","message":"Server is listening on port 7000","timestamp":"2017-12-13T05:35:26.419Z"}
{"level":"info","message":"__ERROR_MIDDLEWARE__","timestamp":"2017-12-13T05:35:26.493Z"}
{"message":"body and content are required","stack":"BadRequestError: body and content are required\n    at Object.<anonymous>.starTrekEpisodesRouter.post (/home/cloud/Documents/codefellows/401/11-express-server/lab-jacob/route/star-trek-episodes-router.js:52:17)\n    at Layer.handle [as handle_request] (/home/cloud/Documents/codefellows/401/11-express-server/lab-jacob/node_modules/express/lib/router/layer.js:95:5)\n    at next (/home/cloud/Documents/codefellows/401/11-express-server/lab-jacob/node_modules/express/lib/router/route.js:137:13)\n    at /home/cloud/Documents/codefellows/401/11-express-server/lab-jacob/node_modules/body-parser/lib/read.js:130:5\n    at invokeCallback (/home/cloud/Documents/codefellows/401/11-express-server/lab-jacob/node_modules/raw-body/index.js:224:16)\n    at done (/home/cloud/Documents/codefellows/401/11-express-server/lab-jacob/node_modules/raw-body/index.js:213:7)\n    at IncomingMessage.onEnd (/home/cloud/Documents/codefellows/401/11-express-server/lab-jacob/node_modules/raw-body/index.js:273:7)\n    at emitNone (events.js:106:13)\n    at IncomingMessage.emit (events.js:208:7)\n    at endReadableNT (_stream_readable.js:1056:12)\n    at _combinedTickCallback (internal/process/next_tick.js:138:11)\n    at process._tickCallback (internal/process/next_tick.js:180:9)","name":"BadRequestError","level":"info","timestamp":"2017-12-13T05:35:26.493Z"}
{"level":"info","message":"Responding with a 400 status and message: body and content are required","timestamp":"2017-12-13T05:35:26.494Z"}
{"level":"info","message":"__ERROR_MIDDLEWARE__","timestamp":"2017-12-13T05:35:26.504Z"}
{"message":"Cast to ObjectId failed for value \"WRONG_ID\" at path \"_id\" for model \"episode\"","stack":"CastError: Cast to ObjectId failed for value \"WRONG_ID\" at path \"_id\" for model \"episode\"\n    at new CastError (/home/cloud/Documents/codefellows/401/11-express-server/lab-jacob/node_modules/mongoose/lib/error/cast.js:27:11)\n    at ObjectId.Object.<anonymous>.ObjectId.cast (/home/cloud/Documents/codefellows/401/11-express-server/lab-jacob/node_modules/mongoose/lib/schema/objectid.js:158:13)\n    at ObjectId.Object.<anonymous>.SchemaType._castForQuery (/home/cloud/Documents/codefellows/401/11-express-server/lab-jacob/node_modules/mongoose/lib/schematype.js:1088:15)\n    at ObjectId.Object.<anonymous>.ObjectId.castForQuery (/home/cloud/Documents/codefellows/401/11-express-server/lab-jacob/node_modules/mongoose/lib/schema/objectid.js:198:15)\n    at ObjectId.Object.<anonymous>.SchemaType.castForQueryWrapper (/home/cloud/Documents/codefellows/401/11-express-server/lab-jacob/node_modules/mongoose/lib/schematype.js:1045:15)\n    at cast (/home/cloud/Documents/codefellows/401/11-express-server/lab-jacob/node_modules/mongoose/lib/cast.js:269:32)\n    at model.Query.Object.<anonymous>.Query.cast (/home/cloud/Documents/codefellows/401/11-express-server/lab-jacob/node_modules/mongoose/lib/query.js:3302:12)\n    at model.Query.Object.<anonymous>.Query._castConditions (/home/cloud/Documents/codefellows/401/11-express-server/lab-jacob/node_modules/mongoose/lib/query.js:1292:10)\n    at model.Query.Object.<anonymous>.Query._findOne (/home/cloud/Documents/codefellows/401/11-express-server/lab-jacob/node_modules/mongoose/lib/query.js:1504:8)\n    at /home/cloud/Documents/codefellows/401/11-express-server/lab-jacob/node_modules/kareem/index.js:250:8\n    at /home/cloud/Documents/codefellows/401/11-express-server/lab-jacob/node_modules/kareem/index.js:23:7\n    at _combinedTickCallback (internal/process/next_tick.js:131:7)\n    at process._tickCallback (internal/process/next_tick.js:180:9)","name":"CastError","stringValue":"\"WRONG_ID\"","kind":"ObjectId","value":"WRONG_ID","path":"_id","level":"info","timestamp":"2017-12-13T05:35:26.504Z"}
{"level":"info","message":"Responding with a 404 status code","timestamp":"2017-12-13T05:35:26.504Z"}
{"level":"info","message":"Server off","timestamp":"2017-12-13T05:35:26.510Z"}
